dsutils/__init__.py
dsutils/base.py
dsutils/exploratory.py
dsutils/jupyter.py
dsutils/preprocess.py
dsutils-0.2.0.dist-info/DESCRIPTION.rst
dsutils-0.2.0.dist-info/METADATA
dsutils-0.2.0.dist-info/RECORD
dsutils-0.2.0.dist-info/WHEEL
dsutils-0.2.0.dist-info/entry_points.txt
dsutils-0.2.0.dist-info/metadata.json
dsutils-0.2.0.dist-info/top_level.txt
